codx/__init__.py
codx/__main__.py
codx/main.py
codx/cli/__init__.py
codx/cli/commands.py
codx/cli/main.py
codx/core/__init__.py
codx/core/database.py
codx/core/models.py
codx/core/schema.sql
codx/tui/__init__.py
codx/tui/app.py
codx/tui/screens.py
codx/utils/__init__.py
codx/utils/display.py
codx/utils/execution.py
codx/utils/search.py
codx/utils/variables.py
codx_snippet_manager-1.0.1.dist-info/METADATA
codx_snippet_manager-1.0.1.dist-info/WHEEL
codx_snippet_manager-1.0.1.dist-info/entry_points.txt
codx_snippet_manager-1.0.1.dist-info/top_level.txt
codx_snippet_manager-1.0.1.dist-info/RECORD
