Metadata-Version: 2.4
Name: codx-snippet-manager
Version: 1.0.1
Summary: A powerful, local-first code snippet manager for the command line with interactive TUI
Author-email: CODX Team <codx@example.com>
Project-URL: Homepage, https://github.com/your-username/codx
Project-URL: Repository, https://github.com/your-username/codx
Project-URL: Issues, https://github.com/your-username/codx/issues
Classifier: Development Status :: 4 - Beta
Classifier: Intended Audience :: Developers
Classifier: License :: OSI Approved :: MIT License
Classifier: Operating System :: OS Independent
Classifier: Programming Language :: Python :: 3
Classifier: Programming Language :: Python :: 3.8
Classifier: Programming Language :: Python :: 3.9
Classifier: Programming Language :: Python :: 3.10
Classifier: Programming Language :: Python :: 3.11
Classifier: Programming Language :: Python :: 3.12
Classifier: Topic :: Terminals
Classifier: Topic :: Utilities
Classifier: Topic :: Software Development :: Libraries
Requires-Python: >=3.8
Requires-Dist: typer>=0.9.0
Requires-Dist: rich>=13.0.0
Requires-Dist: textual>=0.41.0
Requires-Dist: pyperclip>=1.8.0
Requires-Dist: fuzzywuzzy>=0.18.0
Requires-Dist: python-levenshtein>=0.20.0
